data_compressor/.idea/.gitignore
data_compressor/.idea/data_compressor.iml
data_compressor/.idea/inspectionProfiles/profiles_settings.xml
data_compressor/.idea/inspectionProfiles/Project_Default.xml
data_compressor/.idea/misc.xml
data_compressor/.idea/modules.xml
data_compressor/.idea/workspace.xml
data_compressor/__init__.py
data_compressor/config/__init__.py
data_compressor/config/config.py
data_compressor/context/__init__.py
data_compressor/context/compression.py
data_compressor/context/retriever.py
data_compressor/dist/data_compressor-1.0.0.tar.gz
data_compressor/main.py
data_compressor/memory/__init__.py
data_compressor/memory/embeddings.py
data_compressor-1.0.2.dist-info/METADATA
data_compressor-1.0.2.dist-info/WHEEL
data_compressor-1.0.2.dist-info/RECORD
