Metadata-Version: 2.1
Name: data_compressor
Version: 1.0.2
Summary: zuno dx
License: no
Author: Nimisha Bansal
Author-email: nimisha.bansal@cognida.ai
Requires-Python: >=3.11,<3.12
Classifier: License :: Other/Proprietary License
Classifier: Programming Language :: Python :: 3
Classifier: Programming Language :: Python :: 3.11
Requires-Dist: langchain (==0.1.13)
Requires-Dist: langchain-community (==0.0.29)
Requires-Dist: langchain-core (==0.1.34)
Requires-Dist: langchain-text-splitters (==0.0.1)
Requires-Dist: openai (==1.14.3)
Requires-Dist: tiktoken (==0.5.2)
